{
  "problemId": 16953,
  "title": "A → B",
  "timeLimit": "2 초",
  "memoryLimit": "512 MB",
  "description": "<p>정수 A를 B로 바꾸려고 한다. 가능한 연산은 다음과 같은 두 가지이다.</p>\n\n<ul>\n\t<li>2를 곱한다.</li>\n\t<li>1을 수의 가장 오른쪽에 추가한다.&nbsp;</li>\n</ul>\n\n<p>A를 B로 바꾸는데 필요한 연산의 최솟값을 구해보자.</p>",
  "inputDesc": "<p>첫째 줄에 A, B (1 ≤ A &lt; B ≤ 10<sup>9</sup>)가 주어진다.</p>",
  "outputDesc": "<p>A를 B로 바꾸는데 필요한 연산의 최솟값에 1을 더한 값을 출력한다. 만들 수 없는 경우에는 -1을 출력한다.</p>",
  "tags": [
    "성공",
    "그래프 이론",
    "그리디 알고리즘",
    "그래프 탐색",
    "너비 우선 탐색"
  ],
  "fetchedAt": "2026-04-22T02:16:53.821Z"
}
